<?xml version="1.0" encoding="utf-8" ?><dwsync><file name="map.gif" server="pencilmedia.com" local="3376933358" remote="11970617672" /><file name="menu.css" server="pencilmedia.com" local="3376933358" remote="11970617672" /><file name="menuarodwn8_dim_1.gif" server="pencilmedia.com" local="3376933358" remote="11970617672" /><file name="menuarodwn8_hov_1.gif" server="pencilmedia.com" local="3376933358" remote="11970617672" /><file name="menuarodwn8_nrm_1.gif" server="pencilmedia.com" local="3376933358" remote="11970617672" /><file name="menuarorght8_dim_1.gif" server="pencilmedia.com" local="3376933358" remote="11970617672" /><file name="menuarorght8_hov_1.gif" server="pencilmedia.com" local="3376933358" remote="11970617672" /><file name="menuarorght8_nrm_1.gif" server="pencilmedia.com" local="3376933358" remote="11970617672" /><file name="menuaroup8_dim_1.gif" server="pencilmedia.com" local="3376933358" remote="11970617672" /><file name="menuaroup8_nrm_1.gif" server="pencilmedia.com" local="3376933358" remote="11970617672" /><file name="menuchk8_dim_1.gif" server="pencilmedia.com" local="3376933358" remote="11970617672" /><file name="menuchk8_hov_1.gif" server="pencilmedia.com" local="3376933358" remote="11970617672" /><file name="menuchk8_nrm_1.gif" server="pencilmedia.com" local="3376933358" remote="11970617672" /></dwsync>